{
  "match_id": "1106",
  "source_id": "829805",
  "season": 2015,
  "round": "League",
  "match_number": 51,
  "date": "2015-05-14",
  "team1": "Mumbai Indians",
  "team2": "Kolkata Knight Riders",
  "venue": "Wankhede Stadium, Mumbai",
  "result_text": "Mumbai Indians won by 5 runs",
  "innings": [
    {
      "bat_team": "Mumbai Indians",
      "bowl_team": "Kolkata Knight Riders",
      "innings_id": 1,
      "score": {
        "runs": 171,
        "wickets": 4,
        "overs": "20",
        "run_rate": 8.55,
        "declared": false
      },
      "extras": {
        "total": 10,
        "wides": 6,
        "no_balls": 3,
        "byes": 0,
        "leg_byes": 1
      },
      "batsmen": [
        {
          "name": "LMP Simmons",
          "runs": 14,
          "balls": 15,
          "fours": 1,
          "sixes": 1,
          "strike_rate": 93.3,
          "out_desc": "c MK Pandey b M Morkel",
          "is_captain": false,
          "is_keeper": false,
          "not_out": false
        },
        {
          "name": "PA Patel",
          "runs": 21,
          "balls": 14,
          "fours": 3,
          "sixes": 0,
          "strike_rate": 150.0,
          "out_desc": "c MK Pandey b Shakib Al Hasan",
          "is_captain": false,
          "is_keeper": false,
          "not_out": false
        },
        {
          "name": "RG Sharma",
          "runs": 30,
          "balls": 21,
          "fours": 5,
          "sixes": 0,
          "strike_rate": 142.9,
          "out_desc": "b SP Narine",
          "is_captain": false,
          "is_keeper": false,
          "not_out": false
        },
        {
          "name": "AT Rayudu",
          "runs": 2,
          "balls": 3,
          "fours": 0,
          "sixes": 0,
          "strike_rate": 66.7,
          "out_desc": "c AD Russell b Shakib Al Hasan",
          "is_captain": false,
          "is_keeper": false,
          "not_out": false
        },
        {
          "name": "KA Pollard",
          "runs": 33,
          "balls": 38,
          "fours": 1,
          "sixes": 1,
          "strike_rate": 86.8,
          "out_desc": "",
          "is_captain": false,
          "is_keeper": false,
          "not_out": true
        },
        {
          "name": "HH Pandya",
          "runs": 61,
          "balls": 29,
          "fours": 8,
          "sixes": 2,
          "strike_rate": 210.3,
          "out_desc": "",
          "is_captain": false,
          "is_keeper": false,
          "not_out": true
        }
      ],
      "bowlers": [
        {
          "name": "UT Yadav",
          "maidens": 0,
          "runs": 37,
          "wickets": 0,
          "economy": 12.3,
          "wides": 0,
          "no_balls": 1,
          "overs": "3"
        },
        {
          "name": "M Morkel",
          "maidens": 0,
          "runs": 27,
          "wickets": 1,
          "economy": 6.8,
          "wides": 2,
          "no_balls": 1,
          "overs": "4"
        },
        {
          "name": "Shakib Al Hasan",
          "maidens": 0,
          "runs": 22,
          "wickets": 2,
          "economy": 5.5,
          "wides": 1,
          "no_balls": 0,
          "overs": "4"
        },
        {
          "name": "PP Chawla",
          "maidens": 0,
          "runs": 9,
          "wickets": 0,
          "economy": 9.0,
          "wides": 0,
          "no_balls": 0,
          "overs": "1"
        },
        {
          "name": "SP Narine",
          "maidens": 0,
          "runs": 38,
          "wickets": 1,
          "economy": 9.5,
          "wides": 3,
          "no_balls": 0,
          "overs": "4"
        },
        {
          "name": "AD Russell",
          "maidens": 0,
          "runs": 37,
          "wickets": 0,
          "economy": 9.2,
          "wides": 0,
          "no_balls": 1,
          "overs": "4"
        }
      ],
      "fow": [
        {
          "name": "PA Patel",
          "runs": 29,
          "over": "4.2",
          "wkt_n": 1
        },
        {
          "name": "LMP Simmons",
          "runs": 42,
          "over": "5.4",
          "wkt_n": 2
        },
        {
          "name": "AT Rayudu",
          "runs": 47,
          "over": "6.3",
          "wkt_n": 3
        },
        {
          "name": "RG Sharma",
          "runs": 79,
          "over": "11.4",
          "wkt_n": 4
        }
      ],
      "progression": [
        "1,0,0,0,0",
        "2,0,0,0,0",
        "3,1,0,1,1",
        "4,1,0,0,0",
        "5,5,0,4,4",
        "6,6,0,1,1",
        "7,7,0,1,1",
        "8,7,0,0,0",
        "9,7,0,0,0",
        "10,8,0,1,1",
        "11,9,0,1,1",
        "12,10,0,1,1",
        "13,10,0,0,0",
        "14,11,0,1,1",
        "15,11,0,0,0",
        "16,11,0,0,0",
        "17,12,0,1,1",
        "18,16,0,4,4",
        "19,18,0,2,2",
        "20,22,0,4,4",
        "21,24,0,2,2",
        "22,25,0,1,1",
        "23,25,0,0,0",
        "24,25,0,0,0",
        "25,29,0,4,4",
        "26,29,1,0,W",
        "27,29,1,0,0",
        "28,29,1,0,0",
        "29,33,1,4,4",
        "30,34,1,1,1",
        "31,35,1,1,1",
        "32,35,1,0,0",
        "33,42,1,7,Nb/6",
        "34,42,2,0,W",
        "35,44,2,2,Wd",
        "36,46,2,2,2",
        "37,47,2,1,1",
        "38,47,2,0,0",
        "39,47,3,0,W",
        "40,48,3,1,1",
        "41,48,3,0,0",
        "42,48,3,0,0",
        "43,48,3,0,0",
        "44,49,3,1,1",
        "45,49,3,0,0",
        "46,50,3,1,Wd",
        "47,50,3,0,0",
        "48,50,3,0,0",
        "49,50,3,0,0",
        "50,50,3,0,0",
        "51,54,3,4,4",
        "52,58,3,4,4",
        "53,59,3,1,1",
        "54,59,3,0,0",
        "55,60,3,1,1",
        "56,60,3,0,0",
        "57,60,3,0,0",
        "58,62,3,2,2",
        "59,63,3,1,1",
        "60,67,3,4,4",
        "61,68,3,1,1",
        "62,69,3,1,1",
        "63,69,3,0,0",
        "64,69,3,0,0",
        "65,73,3,4,4",
        "66,73,3,0,0",
        "67,74,3,1,1",
        "68,75,3,1,1",
        "69,79,3,4,4",
        "70,79,4,0,W",
        "71,79,4,0,0",
        "72,80,4,1,1",
        "73,81,4,1,1",
        "74,83,4,2,2",
        "75,84,4,1,1",
        "76,85,4,1,1",
        "77,85,4,0,0",
        "78,86,4,1,1",
        "79,86,4,0,0",
        "80,87,4,1,1",
        "81,88,4,1,1",
        "82,89,4,1,1",
        "83,91,4,2,Wd",
        "84,91,4,0,0",
        "85,95,4,4,4",
        "86,95,4,0,0",
        "87,97,4,2,2",
        "88,98,4,1,1",
        "89,98,4,0,0",
        "90,99,4,1,1",
        "91,105,4,6,6",
        "92,107,4,2,Wd",
        "93,109,4,2,Wd",
        "94,110,4,1,1",
        "95,111,4,1,1",
        "96,112,4,1,1",
        "97,113,4,1,1",
        "98,117,4,4,4",
        "99,121,4,4,4",
        "100,125,4,4,4",
        "101,129,4,4,4",
        "102,130,4,1,1",
        "103,131,4,1,1",
        "104,132,4,1,1",
        "105,133,4,1,1",
        "106,134,4,1,1",
        "107,140,4,6,6",
        "108,141,4,1,Wd",
        "109,142,4,1,1",
        "110,147,4,5,Nb/4",
        "111,151,4,4,4",
        "112,157,4,6,6",
        "113,157,4,0,0",
        "114,158,4,1,1",
        "115,162,4,4,4",
        "116,166,4,4,Nb",
        "117,168,4,2,2",
        "118,169,4,1,1",
        "119,170,4,1,1",
        "120,171,4,1,1"
      ]
    },
    {
      "bat_team": "Kolkata Knight Riders",
      "bowl_team": "Mumbai Indians",
      "innings_id": 2,
      "score": {
        "runs": 166,
        "wickets": 7,
        "overs": "20",
        "run_rate": 8.3,
        "declared": false
      },
      "extras": {
        "total": 8,
        "wides": 7,
        "no_balls": 0,
        "byes": 1,
        "leg_byes": 0
      },
      "batsmen": [
        {
          "name": "RV Uthappa",
          "runs": 25,
          "balls": 20,
          "fours": 3,
          "sixes": 1,
          "strike_rate": 125.0,
          "out_desc": "c SL Malinga b Harbhajan Singh",
          "is_captain": false,
          "is_keeper": false,
          "not_out": false
        },
        {
          "name": "G Gambhir",
          "runs": 38,
          "balls": 29,
          "fours": 5,
          "sixes": 0,
          "strike_rate": 131.0,
          "out_desc": "b J Suchith",
          "is_captain": false,
          "is_keeper": false,
          "not_out": false
        },
        {
          "name": "MK Pandey",
          "runs": 1,
          "balls": 1,
          "fours": 0,
          "sixes": 0,
          "strike_rate": 100.0,
          "out_desc": "run out (LMP Simmons)",
          "is_captain": false,
          "is_keeper": false,
          "not_out": false
        },
        {
          "name": "YK Pathan",
          "runs": 52,
          "balls": 37,
          "fours": 5,
          "sixes": 2,
          "strike_rate": 140.5,
          "out_desc": "c PA Patel b KA Pollard",
          "is_captain": false,
          "is_keeper": false,
          "not_out": false
        },
        {
          "name": "Shakib Al Hasan",
          "runs": 23,
          "balls": 15,
          "fours": 3,
          "sixes": 0,
          "strike_rate": 153.3,
          "out_desc": "c HH Pandya b R Vinay Kumar",
          "is_captain": false,
          "is_keeper": false,
          "not_out": false
        },
        {
          "name": "AD Russell",
          "runs": 2,
          "balls": 4,
          "fours": 0,
          "sixes": 0,
          "strike_rate": 50.0,
          "out_desc": "c PA Patel b SL Malinga",
          "is_captain": false,
          "is_keeper": false,
          "not_out": false
        },
        {
          "name": "SA Yadav",
          "runs": 11,
          "balls": 5,
          "fours": 2,
          "sixes": 0,
          "strike_rate": 220.0,
          "out_desc": "c AT Rayudu b MJ McClenaghan",
          "is_captain": false,
          "is_keeper": false,
          "not_out": false
        },
        {
          "name": "PP Chawla",
          "runs": 1,
          "balls": 7,
          "fours": 0,
          "sixes": 0,
          "strike_rate": 14.3,
          "out_desc": "",
          "is_captain": false,
          "is_keeper": false,
          "not_out": true
        },
        {
          "name": "UT Yadav",
          "runs": 5,
          "balls": 2,
          "fours": 1,
          "sixes": 0,
          "strike_rate": 250.0,
          "out_desc": "",
          "is_captain": false,
          "is_keeper": false,
          "not_out": true
        }
      ],
      "bowlers": [
        {
          "name": "SL Malinga",
          "maidens": 0,
          "runs": 31,
          "wickets": 1,
          "economy": 7.8,
          "wides": 0,
          "no_balls": 0,
          "overs": "4"
        },
        {
          "name": "MJ McClenaghan",
          "maidens": 0,
          "runs": 31,
          "wickets": 1,
          "economy": 7.8,
          "wides": 3,
          "no_balls": 0,
          "overs": "4"
        },
        {
          "name": "R Vinay Kumar",
          "maidens": 0,
          "runs": 33,
          "wickets": 1,
          "economy": 8.2,
          "wides": 0,
          "no_balls": 0,
          "overs": "4"
        },
        {
          "name": "Harbhajan Singh",
          "maidens": 0,
          "runs": 31,
          "wickets": 1,
          "economy": 7.8,
          "wides": 3,
          "no_balls": 0,
          "overs": "4"
        },
        {
          "name": "J Suchith",
          "maidens": 0,
          "runs": 23,
          "wickets": 1,
          "economy": 11.5,
          "wides": 0,
          "no_balls": 0,
          "overs": "2"
        },
        {
          "name": "HH Pandya",
          "maidens": 0,
          "runs": 10,
          "wickets": 0,
          "economy": 10.0,
          "wides": 0,
          "no_balls": 0,
          "overs": "1"
        },
        {
          "name": "KA Pollard",
          "maidens": 0,
          "runs": 6,
          "wickets": 1,
          "economy": 6.0,
          "wides": 1,
          "no_balls": 0,
          "overs": "1"
        }
      ],
      "fow": [
        {
          "name": "RV Uthappa",
          "runs": 45,
          "over": "5.3",
          "wkt_n": 1
        },
        {
          "name": "MK Pandey",
          "runs": 46,
          "over": "5.5",
          "wkt_n": 2
        },
        {
          "name": "G Gambhir",
          "runs": 88,
          "over": "11",
          "wkt_n": 3
        },
        {
          "name": "Shakib Al Hasan",
          "runs": 118,
          "over": "14.2",
          "wkt_n": 4
        },
        {
          "name": "AD Russell",
          "runs": 128,
          "over": "15.5",
          "wkt_n": 5
        },
        {
          "name": "SA Yadav",
          "runs": 144,
          "over": "17.1",
          "wkt_n": 6
        },
        {
          "name": "YK Pathan",
          "runs": 160,
          "over": "19.1",
          "wkt_n": 7
        }
      ],
      "progression": [
        "1,2,0,2,2",
        "2,6,0,4,4",
        "3,6,0,0,0",
        "4,6,0,0,0",
        "5,7,0,1,1",
        "6,7,0,0,0",
        "7,7,0,0,0",
        "8,8,0,1,1",
        "9,8,0,0,0",
        "10,12,0,4,4",
        "11,12,0,0,0",
        "12,12,0,0,0",
        "13,13,0,1,1",
        "14,15,0,2,2",
        "15,19,0,4,4",
        "16,19,0,0,0",
        "17,20,0,1,1",
        "18,20,0,0,0",
        "19,24,0,4,4",
        "20,25,0,1,1",
        "21,25,0,0,0",
        "22,25,0,0,0",
        "23,29,0,4,4",
        "24,29,0,0,0",
        "25,30,0,1,1",
        "26,34,0,4,4",
        "27,34,0,0,0",
        "28,35,0,1,1",
        "29,37,0,2,Wd",
        "30,38,0,1,1",
        "31,44,0,6,6",
        "32,45,0,1,Wd",
        "33,45,1,0,W",
        "34,46,1,1,1",
        "35,46,2,0,W",
        "36,50,2,4,4",
        "37,51,2,1,1",
        "38,51,2,0,0",
        "39,52,2,1,1",
        "40,52,2,0,0",
        "41,53,2,1,1",
        "42,54,2,1,1",
        "43,56,2,2,Wd",
        "44,57,2,1,1",
        "45,57,2,0,0",
        "46,57,2,0,0",
        "47,58,2,1,Wd",
        "48,58,2,0,0",
        "49,60,2,2,2",
        "50,61,2,1,1",
        "51,61,2,0,0",
        "52,65,2,4,4",
        "53,66,2,1,1",
        "54,67,2,1,1",
        "55,71,2,4,4",
        "56,72,2,1,1",
        "57,72,2,0,0",
        "58,73,2,1,1",
        "59,73,2,0,0",
        "60,74,2,1,1",
        "61,75,2,1,1",
        "62,81,2,6,6",
        "63,82,2,1,1",
        "64,86,2,4,4",
        "65,88,2,2,2",
        "66,88,3,0,W",
        "67,89,3,1,1",
        "68,89,3,0,0",
        "69,93,3,4,4",
        "70,94,3,1,1",
        "71,95,3,1,1",
        "72,96,3,1,1",
        "73,100,3,4,4",
        "74,102,3,2,2",
        "75,103,3,1,1",
        "76,104,3,1,1",
        "77,106,3,2,2",
        "78,106,3,0,0",
        "79,107,3,1,1",
        "80,107,3,0,0",
        "81,108,3,1,1",
        "82,110,3,2,Wd",
        "83,115,3,5,Wd/4",
        "84,116,3,1,1",
        "85,118,3,2,2",
        "86,118,4,0,W",
        "87,120,4,2,2",
        "88,121,4,1,1",
        "89,121,4,0,0",
        "90,122,4,1,1",
        "91,123,4,1,1",
        "92,127,4,4,4",
        "93,127,4,0,0",
        "94,128,4,1,1",
        "95,128,5,0,W",
        "96,130,5,2,2",
        "97,134,5,4,4",
        "98,135,5,1,1",
        "99,139,5,4,4",
        "100,143,5,4,4",
        "101,144,5,1,1",
        "102,144,5,0,0",
        "103,144,6,0,W",
        "104,144,6,0,0",
        "105,148,6,4,4",
        "106,149,6,1,1",
        "107,150,6,1,1",
        "108,151,6,1,1",
        "109,152,6,1,1",
        "110,152,6,0,0",
        "111,153,6,1,1",
        "112,159,6,6,6",
        "113,160,6,1,1",
        "114,160,6,0,0",
        "115,160,7,0,W",
        "116,164,7,4,4",
        "117,165,7,1,1",
        "118,166,7,1,Wd",
        "119,166,7,0,0",
        "120,166,7,0,0"
      ]
    }
  ],
  "error": null
}