{
  "match_id": "225",
  "source_id": "1216537",
  "season": 2020,
  "round": "League",
  "match_number": 50,
  "date": "2020-10-30",
  "team1": "Kings XI Punjab",
  "team2": "Rajasthan Royals",
  "venue": "Sheikh Zayed Stadium, Abu Dhabi",
  "result_text": "Rajasthan Royals won by 7 wkts",
  "innings": [
    {
      "bat_team": "Kings XI Punjab",
      "bowl_team": "Rajasthan Royals",
      "innings_id": 1,
      "score": {
        "runs": 185,
        "wickets": 4,
        "overs": "20",
        "run_rate": 9.25,
        "declared": false
      },
      "extras": {
        "total": 11,
        "wides": 8,
        "no_balls": 2,
        "byes": 0,
        "leg_byes": 1
      },
      "batsmen": [
        {
          "name": "KL Rahul",
          "runs": 46,
          "balls": 41,
          "fours": 3,
          "sixes": 2,
          "strike_rate": 112.2,
          "out_desc": "c R Tewatia b BA Stokes",
          "is_captain": false,
          "is_keeper": false,
          "not_out": false
        },
        {
          "name": "Mandeep Singh",
          "runs": 0,
          "balls": 1,
          "fours": 0,
          "sixes": 0,
          "strike_rate": 0.0,
          "out_desc": "c BA Stokes b JC Archer",
          "is_captain": false,
          "is_keeper": false,
          "not_out": false
        },
        {
          "name": "CH Gayle",
          "runs": 99,
          "balls": 63,
          "fours": 6,
          "sixes": 8,
          "strike_rate": 157.1,
          "out_desc": "b JC Archer",
          "is_captain": false,
          "is_keeper": false,
          "not_out": false
        },
        {
          "name": "N Pooran",
          "runs": 22,
          "balls": 9,
          "fours": 0,
          "sixes": 3,
          "strike_rate": 244.4,
          "out_desc": "c R Tewatia b BA Stokes",
          "is_captain": false,
          "is_keeper": false,
          "not_out": false
        },
        {
          "name": "GJ Maxwell",
          "runs": 6,
          "balls": 5,
          "fours": 1,
          "sixes": 0,
          "strike_rate": 120.0,
          "out_desc": "",
          "is_captain": false,
          "is_keeper": false,
          "not_out": true
        },
        {
          "name": "DJ Hooda",
          "runs": 1,
          "balls": 1,
          "fours": 0,
          "sixes": 0,
          "strike_rate": 100.0,
          "out_desc": "",
          "is_captain": false,
          "is_keeper": false,
          "not_out": true
        }
      ],
      "bowlers": [
        {
          "name": "JC Archer",
          "maidens": 0,
          "runs": 26,
          "wickets": 2,
          "economy": 6.5,
          "wides": 0,
          "no_balls": 0,
          "overs": "4"
        },
        {
          "name": "VR Aaron",
          "maidens": 0,
          "runs": 47,
          "wickets": 0,
          "economy": 11.8,
          "wides": 5,
          "no_balls": 1,
          "overs": "4"
        },
        {
          "name": "Kartik Tyagi",
          "maidens": 0,
          "runs": 47,
          "wickets": 0,
          "economy": 11.8,
          "wides": 0,
          "no_balls": 1,
          "overs": "4"
        },
        {
          "name": "S Gopal",
          "maidens": 0,
          "runs": 10,
          "wickets": 0,
          "economy": 10.0,
          "wides": 0,
          "no_balls": 0,
          "overs": "1"
        },
        {
          "name": "BA Stokes",
          "maidens": 0,
          "runs": 32,
          "wickets": 2,
          "economy": 8.0,
          "wides": 3,
          "no_balls": 0,
          "overs": "4"
        },
        {
          "name": "R Tewatia",
          "maidens": 0,
          "runs": 22,
          "wickets": 0,
          "economy": 7.3,
          "wides": 0,
          "no_balls": 0,
          "overs": "3"
        }
      ],
      "fow": [
        {
          "name": "Mandeep Singh",
          "runs": 1,
          "over": "1",
          "wkt_n": 1
        },
        {
          "name": "KL Rahul",
          "runs": 121,
          "over": "14.4",
          "wkt_n": 2
        },
        {
          "name": "N Pooran",
          "runs": 162,
          "over": "18",
          "wkt_n": 3
        },
        {
          "name": "CH Gayle",
          "runs": 184,
          "over": "19.4",
          "wkt_n": 4
        }
      ],
      "progression": [
        "1,0,0,0,0",
        "2,0,0,0,0",
        "3,0,0,0,0",
        "4,0,0,0,0",
        "5,1,0,1,1",
        "6,1,1,0,W",
        "7,3,1,2,Wd",
        "8,3,1,0,0",
        "9,3,1,0,0",
        "10,3,1,0,0",
        "11,3,1,0,0",
        "12,9,1,6,Wd/Wd/4",
        "13,9,1,0,0",
        "14,13,1,4,4",
        "15,13,1,0,0",
        "16,13,1,0,0",
        "17,14,1,1,1",
        "18,14,1,0,0",
        "19,14,1,0,0",
        "20,15,1,1,1",
        "21,22,1,7,Wd/6",
        "22,24,1,2,2",
        "23,25,1,1,1",
        "24,25,1,0,0",
        "25,25,1,0,0",
        "26,29,1,4,4",
        "27,35,1,6,6",
        "28,39,1,4,4",
        "29,39,1,0,0",
        "30,39,1,0,0",
        "31,41,1,2,2",
        "32,47,1,6,6",
        "33,47,1,0,0",
        "34,49,1,2,2",
        "35,49,1,0,0",
        "36,53,1,4,4",
        "37,53,1,0,0",
        "38,54,1,1,1",
        "39,55,1,1,1",
        "40,61,1,6,6",
        "41,62,1,1,1",
        "42,63,1,1,1",
        "43,64,1,1,1",
        "44,68,1,4,4",
        "45,69,1,1,1",
        "46,70,1,1,1",
        "47,70,1,0,0",
        "48,71,1,1,1",
        "49,71,1,0,0",
        "50,71,1,0,0",
        "51,72,1,1,1",
        "52,73,1,1,1",
        "53,73,1,0,0",
        "54,73,1,0,0",
        "55,73,1,0,0",
        "56,79,1,6,6",
        "57,80,1,1,1",
        "58,80,1,0,0",
        "59,81,1,1,1",
        "60,81,1,0,0",
        "61,82,1,1,1",
        "62,83,1,1,1",
        "63,89,1,6,6",
        "64,89,1,0,0",
        "65,90,1,1,1",
        "66,91,1,1,1",
        "67,92,1,1,1",
        "68,93,1,1,1",
        "69,94,1,1,1",
        "70,95,1,1,1",
        "71,96,1,1,1",
        "72,97,1,1,1",
        "73,97,1,0,0",
        "74,98,1,1,1",
        "75,99,1,1,1",
        "76,105,1,6,6",
        "77,106,1,1,1",
        "78,107,1,1,1",
        "79,107,1,0,0",
        "80,111,1,4,4",
        "81,112,1,1,1",
        "82,116,1,4,4",
        "83,118,1,2,2",
        "84,118,1,0,0",
        "85,118,1,0,0",
        "86,119,1,1,1",
        "87,121,1,2,Wd",
        "88,121,2,0,W",
        "89,123,2,2,Wd",
        "90,123,2,0,0",
        "91,123,2,0,0",
        "92,123,2,0,0",
        "93,124,2,1,1",
        "94,130,2,6,6",
        "95,130,2,0,0",
        "96,137,2,7,Nb/6",
        "97,137,2,0,0",
        "98,138,2,1,1",
        "99,139,2,1,1",
        "100,140,2,1,1",
        "101,142,2,2,2",
        "102,148,2,6,6",
        "103,152,2,4,4",
        "104,154,2,2,Wd",
        "105,155,2,1,1",
        "106,161,2,6,6",
        "107,162,2,1,1",
        "108,162,3,0,W",
        "109,163,3,1,1",
        "110,168,3,5,4",
        "111,168,3,0,0",
        "112,169,3,1,1",
        "113,175,3,6,6",
        "114,176,3,1,1",
        "115,177,3,1,1",
        "116,178,3,1,1",
        "117,184,3,6,6",
        "118,184,4,0,W",
        "119,185,4,1,1",
        "120,185,4,0,0"
      ]
    },
    {
      "bat_team": "Rajasthan Royals",
      "bowl_team": "Kings XI Punjab",
      "innings_id": 2,
      "score": {
        "runs": 186,
        "wickets": 3,
        "overs": "17.3",
        "run_rate": 10.63,
        "declared": false
      },
      "extras": {
        "total": 5,
        "wides": 3,
        "no_balls": 0,
        "byes": 0,
        "leg_byes": 2
      },
      "batsmen": [
        {
          "name": "RV Uthappa",
          "runs": 30,
          "balls": 23,
          "fours": 1,
          "sixes": 2,
          "strike_rate": 130.4,
          "out_desc": "c N Pooran b M Ashwin",
          "is_captain": false,
          "is_keeper": false,
          "not_out": false
        },
        {
          "name": "BA Stokes",
          "runs": 50,
          "balls": 26,
          "fours": 6,
          "sixes": 3,
          "strike_rate": 192.3,
          "out_desc": "c DJ Hooda b CJ Jordan",
          "is_captain": false,
          "is_keeper": false,
          "not_out": false
        },
        {
          "name": "SV Samson",
          "runs": 48,
          "balls": 25,
          "fours": 4,
          "sixes": 3,
          "strike_rate": 192.0,
          "out_desc": "run out",
          "is_captain": false,
          "is_keeper": false,
          "not_out": false
        },
        {
          "name": "SPD Smith",
          "runs": 31,
          "balls": 20,
          "fours": 5,
          "sixes": 0,
          "strike_rate": 155.0,
          "out_desc": "",
          "is_captain": false,
          "is_keeper": false,
          "not_out": true
        },
        {
          "name": "JC Buttler",
          "runs": 22,
          "balls": 11,
          "fours": 1,
          "sixes": 2,
          "strike_rate": 200.0,
          "out_desc": "",
          "is_captain": false,
          "is_keeper": false,
          "not_out": true
        }
      ],
      "bowlers": [
        {
          "name": "Arshdeep Singh",
          "maidens": 0,
          "runs": 34,
          "wickets": 0,
          "economy": 11.3,
          "wides": 0,
          "no_balls": 0,
          "overs": "3"
        },
        {
          "name": "Mohammed Shami",
          "maidens": 0,
          "runs": 36,
          "wickets": 0,
          "economy": 12.0,
          "wides": 0,
          "no_balls": 0,
          "overs": "3"
        },
        {
          "name": "M Ashwin",
          "maidens": 0,
          "runs": 43,
          "wickets": 1,
          "economy": 10.8,
          "wides": 0,
          "no_balls": 0,
          "overs": "4"
        },
        {
          "name": "CJ Jordan",
          "maidens": 0,
          "runs": 44,
          "wickets": 1,
          "economy": 12.6,
          "wides": 2,
          "no_balls": 0,
          "overs": "3.3"
        },
        {
          "name": "Ravi Bishnoi",
          "maidens": 0,
          "runs": 27,
          "wickets": 0,
          "economy": 6.8,
          "wides": 1,
          "no_balls": 0,
          "overs": "4"
        }
      ],
      "fow": [
        {
          "name": "BA Stokes",
          "runs": 60,
          "over": "5.3",
          "wkt_n": 1
        },
        {
          "name": "RV Uthappa",
          "runs": 111,
          "over": "10.5",
          "wkt_n": 2
        },
        {
          "name": "SV Samson",
          "runs": 145,
          "over": "14.2",
          "wkt_n": 3
        }
      ],
      "progression": [
        "1,0,0,0,0",
        "2,1,0,1,1",
        "3,3,0,2,2",
        "4,5,0,2,2",
        "5,5,0,0,0",
        "6,9,0,4,4",
        "7,10,0,1,1",
        "8,14,0,4,4",
        "9,14,0,0,0",
        "10,14,0,0,0",
        "11,15,0,1,1",
        "12,21,0,6,6",
        "13,21,0,0,0",
        "14,25,0,4,4",
        "15,26,0,1,1",
        "16,27,0,1,1",
        "17,31,0,4,4",
        "18,32,0,1,1",
        "19,32,0,0,0",
        "20,32,0,0,0",
        "21,36,0,4,4",
        "22,42,0,6,6",
        "23,48,0,6,6",
        "24,48,0,0,0",
        "25,49,0,1,1",
        "26,53,0,4,4",
        "27,53,0,0,0",
        "28,53,0,0,0",
        "29,54,0,1,1",
        "30,54,0,0,0",
        "31,60,0,6,6",
        "32,60,0,0,0",
        "33,60,1,0,W",
        "34,61,1,1,1",
        "35,62,1,1,1",
        "36,66,1,4,4",
        "37,67,1,1,1",
        "38,67,1,0,0",
        "39,68,1,1,1",
        "40,69,1,1,1",
        "41,70,1,1,1",
        "42,71,1,1,1",
        "43,72,1,1,1",
        "44,72,1,0,0",
        "45,73,1,1,1",
        "46,74,1,1,1",
        "47,75,1,1,1",
        "48,79,1,4,4",
        "49,85,1,6,6",
        "50,86,1,1,1",
        "51,87,1,1,1",
        "52,88,1,1,1",
        "53,89,1,1,1",
        "54,93,1,4,4",
        "55,94,1,1,Wd",
        "56,95,1,1,1",
        "57,101,1,6,6",
        "58,101,1,0,0",
        "59,102,1,1,1",
        "60,103,1,1,1",
        "61,104,1,1,1",
        "62,105,1,1,1",
        "63,105,1,0,0",
        "64,111,1,6,6",
        "65,111,2,0,W",
        "66,112,2,1,1",
        "67,114,2,2,2",
        "68,118,2,4,4",
        "69,118,2,0,0",
        "70,118,2,0,0",
        "71,119,2,1,1",
        "72,119,2,0,0",
        "73,120,2,1,1",
        "74,121,2,1,1",
        "75,122,2,1,1",
        "76,122,2,0,0",
        "77,128,2,6,6",
        "78,132,2,4,4",
        "79,132,2,0,0",
        "80,133,2,1,1",
        "81,137,2,4,4",
        "82,139,2,2,2",
        "83,140,2,1,1",
        "84,144,2,4,4",
        "85,145,2,1,1",
        "86,145,3,0,W",
        "87,145,3,0,0",
        "88,145,3,0,0",
        "89,146,3,1,1",
        "90,146,3,0,0",
        "91,148,3,2,2",
        "92,149,3,1,1",
        "93,150,3,1,1",
        "94,150,3,0,0",
        "95,150,3,0,0",
        "96,156,3,6,6",
        "97,160,3,4,4",
        "98,164,3,4,4",
        "99,166,3,2,2",
        "100,170,3,4,4",
        "101,171,3,1,1",
        "102,175,3,4,4",
        "103,177,3,2,Wd",
        "104,183,3,6,6",
        "105,185,3,2,2"
      ]
    }
  ],
  "error": null
}