{
  "match_id": "490",
  "source_id": "1426281",
  "season": 2024,
  "round": "League",
  "match_number": 43,
  "date": "2024-04-27",
  "team1": "Delhi Capitals",
  "team2": "Mumbai Indians",
  "venue": "Arun Jaitley Stadium, Delhi, Delhi",
  "result_text": "Delhi Capitals won by 10 runs",
  "innings": [
    {
      "bat_team": "Delhi Capitals",
      "bowl_team": "Mumbai Indians",
      "innings_id": 1,
      "score": {
        "runs": 257,
        "wickets": 4,
        "overs": "20",
        "run_rate": 12.85,
        "declared": false
      },
      "extras": {
        "total": 8,
        "wides": 6,
        "no_balls": 1,
        "byes": 0,
        "leg_byes": 1
      },
      "batsmen": [
        {
          "name": "J Fraser-McGurk",
          "runs": 84,
          "balls": 26,
          "fours": 11,
          "sixes": 6,
          "strike_rate": 323.1,
          "out_desc": "c Mohammad Nabi b PP Chawla",
          "is_captain": false,
          "is_keeper": false,
          "not_out": false
        },
        {
          "name": "Abishek Porel",
          "runs": 36,
          "balls": 27,
          "fours": 3,
          "sixes": 1,
          "strike_rate": 133.3,
          "out_desc": "c Ishan Kishan b Mohammad Nabi",
          "is_captain": false,
          "is_keeper": false,
          "not_out": false
        },
        {
          "name": "SD Hope",
          "runs": 41,
          "balls": 17,
          "fours": 0,
          "sixes": 5,
          "strike_rate": 241.2,
          "out_desc": "c Tilak Varma b L Wood",
          "is_captain": false,
          "is_keeper": false,
          "not_out": false
        },
        {
          "name": "RR Pant",
          "runs": 29,
          "balls": 19,
          "fours": 2,
          "sixes": 2,
          "strike_rate": 152.6,
          "out_desc": "c RG Sharma b JJ Bumrah",
          "is_captain": false,
          "is_keeper": false,
          "not_out": false
        },
        {
          "name": "T Stubbs",
          "runs": 48,
          "balls": 25,
          "fours": 6,
          "sixes": 2,
          "strike_rate": 192.0,
          "out_desc": "",
          "is_captain": false,
          "is_keeper": false,
          "not_out": true
        },
        {
          "name": "AR Patel",
          "runs": 11,
          "balls": 6,
          "fours": 0,
          "sixes": 1,
          "strike_rate": 183.3,
          "out_desc": "",
          "is_captain": false,
          "is_keeper": false,
          "not_out": true
        }
      ],
      "bowlers": [
        {
          "name": "L Wood",
          "maidens": 0,
          "runs": 68,
          "wickets": 1,
          "economy": 17.0,
          "wides": 0,
          "no_balls": 0,
          "overs": "4"
        },
        {
          "name": "JJ Bumrah",
          "maidens": 0,
          "runs": 35,
          "wickets": 1,
          "economy": 8.8,
          "wides": 2,
          "no_balls": 1,
          "overs": "4"
        },
        {
          "name": "N Thushara",
          "maidens": 0,
          "runs": 56,
          "wickets": 0,
          "economy": 14.0,
          "wides": 2,
          "no_balls": 0,
          "overs": "4"
        },
        {
          "name": "PP Chawla",
          "maidens": 0,
          "runs": 36,
          "wickets": 1,
          "economy": 9.0,
          "wides": 2,
          "no_balls": 0,
          "overs": "4"
        },
        {
          "name": "HH Pandya",
          "maidens": 0,
          "runs": 41,
          "wickets": 0,
          "economy": 20.5,
          "wides": 0,
          "no_balls": 0,
          "overs": "2"
        },
        {
          "name": "Mohammad Nabi",
          "maidens": 0,
          "runs": 20,
          "wickets": 1,
          "economy": 10.0,
          "wides": 0,
          "no_balls": 0,
          "overs": "2"
        }
      ],
      "fow": [
        {
          "name": "J Fraser-McGurk",
          "runs": 114,
          "over": "7.3",
          "wkt_n": 1
        },
        {
          "name": "Abishek Porel",
          "runs": 127,
          "over": "9.4",
          "wkt_n": 2
        },
        {
          "name": "SD Hope",
          "runs": 180,
          "over": "13.4",
          "wkt_n": 3
        },
        {
          "name": "RR Pant",
          "runs": 235,
          "over": "18.1",
          "wkt_n": 4
        }
      ],
      "progression": [
        "1,4,0,4,4",
        "2,8,0,4,4",
        "3,14,0,6,6",
        "4,14,0,0,0",
        "5,18,0,4,4",
        "6,19,0,1,1",
        "7,30,0,11,6/4",
        "8,31,0,1,1",
        "9,31,0,0,0",
        "10,31,0,0,0",
        "11,33,0,2,Wd",
        "12,37,0,4,4",
        "13,41,0,4,4",
        "14,42,0,1,1",
        "15,46,0,4,4",
        "16,51,0,5,Wd/4",
        "17,55,0,4,4",
        "18,55,0,0,0",
        "19,56,0,1,1",
        "20,62,0,6,6",
        "21,66,0,4,4",
        "22,67,0,1,1",
        "23,68,0,1,1",
        "24,69,0,1,1",
        "25,73,0,4,4",
        "26,73,0,0,0",
        "27,79,0,6,6",
        "28,79,0,0,0",
        "29,83,0,4,4",
        "30,89,0,6,6",
        "31,89,0,0,0",
        "32,89,0,0,0",
        "33,91,0,2,2",
        "34,91,0,0,0",
        "35,91,0,0,0",
        "36,92,0,1,1",
        "37,92,0,0,0",
        "38,92,0,0,0",
        "39,96,0,4,4",
        "40,102,0,6,6",
        "41,107,0,5,5",
        "42,113,0,6,6",
        "43,114,0,1,1",
        "44,114,0,0,0",
        "45,114,1,0,W",
        "46,114,1,0,0",
        "47,115,1,1,1",
        "48,116,1,1,1",
        "49,118,1,2,2",
        "50,122,1,4,4",
        "51,122,1,0,0",
        "52,123,1,1,1",
        "53,124,1,1,1",
        "54,124,1,0,0",
        "55,125,1,1,1",
        "56,126,1,1,1",
        "57,127,1,1,1",
        "58,127,2,0,W",
        "59,127,2,0,0",
        "60,128,2,1,1",
        "61,128,2,0,0",
        "62,129,2,1,1",
        "63,135,2,6,6",
        "64,136,2,1,1",
        "65,137,2,1,1",
        "66,138,2,1,1",
        "67,139,2,1,1",
        "68,140,2,1,1",
        "69,146,2,6,6",
        "70,147,2,1,1",
        "71,148,2,1,1",
        "72,154,2,6,6",
        "73,154,2,0,0",
        "74,158,2,4,4",
        "75,159,2,1,1",
        "76,160,2,1,1",
        "77,166,2,6,6",
        "78,166,2,0,0",
        "79,172,2,6,6",
        "80,178,2,6,6",
        "81,180,2,2,2",
        "82,180,3,0,W",
        "83,180,3,0,0",
        "84,181,3,1,1",
        "85,184,3,3,Wd",
        "86,184,3,0,0",
        "87,184,3,0,0",
        "88,186,3,2,Wd",
        "89,186,3,0,0",
        "90,190,3,4,4",
        "91,191,3,1,1",
        "92,197,3,6,6",
        "93,198,3,1,1",
        "94,198,3,0,0",
        "95,198,3,0,0",
        "96,199,3,1,1",
        "97,203,3,4,4",
        "98,204,3,1,1",
        "99,205,3,1,1",
        "100,206,3,1,1",
        "101,207,3,1,1",
        "102,208,3,1,1",
        "103,212,3,4,4",
        "104,216,3,4,4",
        "105,222,3,6,6",
        "106,226,3,4,4",
        "107,230,3,4,4",
        "108,234,3,4,4",
        "109,235,4,1,Wd/W",
        "110,236,4,1,1",
        "111,237,4,1,1",
        "112,238,4,1,1",
        "113,239,4,1,1",
        "114,240,4,1,1",
        "115,241,4,1,1",
        "116,247,4,6,6",
        "117,249,4,2,Wd",
        "118,255,4,6,6",
        "119,256,4,1,1",
        "120,257,4,1,1"
      ]
    },
    {
      "bat_team": "Mumbai Indians",
      "bowl_team": "Delhi Capitals",
      "innings_id": 2,
      "score": {
        "runs": 247,
        "wickets": 9,
        "overs": "20",
        "run_rate": 12.35,
        "declared": false
      },
      "extras": {
        "total": 17,
        "wides": 12,
        "no_balls": 1,
        "byes": 2,
        "leg_byes": 2
      },
      "batsmen": [
        {
          "name": "Ishan Kishan",
          "runs": 20,
          "balls": 14,
          "fours": 4,
          "sixes": 0,
          "strike_rate": 142.9,
          "out_desc": "c AR Patel b Mukesh Kumar",
          "is_captain": false,
          "is_keeper": false,
          "not_out": false
        },
        {
          "name": "RG Sharma",
          "runs": 8,
          "balls": 7,
          "fours": 1,
          "sixes": 0,
          "strike_rate": 114.3,
          "out_desc": "c SD Hope b KK Ahmed",
          "is_captain": false,
          "is_keeper": false,
          "not_out": false
        },
        {
          "name": "SA Yadav",
          "runs": 26,
          "balls": 13,
          "fours": 3,
          "sixes": 2,
          "strike_rate": 200.0,
          "out_desc": "c LB Williams b KK Ahmed",
          "is_captain": false,
          "is_keeper": false,
          "not_out": false
        },
        {
          "name": "Tilak Varma",
          "runs": 63,
          "balls": 32,
          "fours": 4,
          "sixes": 4,
          "strike_rate": 196.9,
          "out_desc": "run out (Sumit Kumar / RR Pant)",
          "is_captain": false,
          "is_keeper": false,
          "not_out": false
        },
        {
          "name": "HH Pandya",
          "runs": 46,
          "balls": 24,
          "fours": 4,
          "sixes": 3,
          "strike_rate": 191.7,
          "out_desc": "c Mukesh Kumar b Rasikh Salam",
          "is_captain": false,
          "is_keeper": false,
          "not_out": false
        },
        {
          "name": "N Wadhera",
          "runs": 4,
          "balls": 2,
          "fours": 1,
          "sixes": 0,
          "strike_rate": 200.0,
          "out_desc": "c RR Pant b Rasikh Salam",
          "is_captain": false,
          "is_keeper": false,
          "not_out": false
        },
        {
          "name": "TH David",
          "runs": 37,
          "balls": 17,
          "fours": 2,
          "sixes": 3,
          "strike_rate": 217.6,
          "out_desc": "lbw b Mukesh Kumar",
          "is_captain": false,
          "is_keeper": false,
          "not_out": false
        },
        {
          "name": "Mohammad Nabi",
          "runs": 7,
          "balls": 4,
          "fours": 0,
          "sixes": 1,
          "strike_rate": 175.0,
          "out_desc": "c SD Hope b Rasikh Salam",
          "is_captain": false,
          "is_keeper": false,
          "not_out": false
        },
        {
          "name": "PP Chawla",
          "runs": 10,
          "balls": 4,
          "fours": 1,
          "sixes": 1,
          "strike_rate": 250.0,
          "out_desc": "c SD Hope b Mukesh Kumar",
          "is_captain": false,
          "is_keeper": false,
          "not_out": false
        },
        {
          "name": "L Wood",
          "runs": 9,
          "balls": 3,
          "fours": 0,
          "sixes": 1,
          "strike_rate": 300.0,
          "out_desc": "",
          "is_captain": false,
          "is_keeper": false,
          "not_out": true
        }
      ],
      "bowlers": [
        {
          "name": "LB Williams",
          "maidens": 0,
          "runs": 34,
          "wickets": 0,
          "economy": 11.3,
          "wides": 8,
          "no_balls": 1,
          "overs": "3"
        },
        {
          "name": "KK Ahmed",
          "maidens": 0,
          "runs": 45,
          "wickets": 2,
          "economy": 11.2,
          "wides": 0,
          "no_balls": 0,
          "overs": "4"
        },
        {
          "name": "Mukesh Kumar",
          "maidens": 0,
          "runs": 59,
          "wickets": 3,
          "economy": 14.8,
          "wides": 0,
          "no_balls": 0,
          "overs": "4"
        },
        {
          "name": "Kuldeep Yadav",
          "maidens": 0,
          "runs": 47,
          "wickets": 0,
          "economy": 15.7,
          "wides": 1,
          "no_balls": 0,
          "overs": "3"
        },
        {
          "name": "AR Patel",
          "maidens": 0,
          "runs": 24,
          "wickets": 0,
          "economy": 12.0,
          "wides": 0,
          "no_balls": 0,
          "overs": "2"
        },
        {
          "name": "Rasikh Salam",
          "maidens": 0,
          "runs": 34,
          "wickets": 3,
          "economy": 8.5,
          "wides": 3,
          "no_balls": 0,
          "overs": "4"
        }
      ],
      "fow": [
        {
          "name": "RG Sharma",
          "runs": 35,
          "over": "3.1",
          "wkt_n": 1
        },
        {
          "name": "Ishan Kishan",
          "runs": 45,
          "over": "4.1",
          "wkt_n": 2
        },
        {
          "name": "SA Yadav",
          "runs": 65,
          "over": "6",
          "wkt_n": 3
        },
        {
          "name": "HH Pandya",
          "runs": 136,
          "over": "12.3",
          "wkt_n": 4
        },
        {
          "name": "N Wadhera",
          "runs": 140,
          "over": "12.5",
          "wkt_n": 5
        },
        {
          "name": "TH David",
          "runs": 210,
          "over": "17.4",
          "wkt_n": 6
        },
        {
          "name": "Mohammad Nabi",
          "runs": 223,
          "over": "18.3",
          "wkt_n": 7
        },
        {
          "name": "Tilak Varma",
          "runs": 234,
          "over": "19.1",
          "wkt_n": 8
        },
        {
          "name": "PP Chawla",
          "runs": 247,
          "over": "20",
          "wkt_n": 9
        }
      ],
      "progression": [
        "1,0,0,0,0",
        "2,1,0,1,1",
        "3,4,0,3,Wd",
        "4,4,0,0,0",
        "5,5,0,1,Nb",
        "6,14,0,9,Wd/4",
        "7,15,0,1,1",
        "8,16,0,1,1",
        "9,20,0,4,4",
        "10,24,0,4,4",
        "11,28,0,4,4",
        "12,29,0,1,1",
        "13,33,0,4,4",
        "14,33,0,0,0",
        "15,33,0,0,0",
        "16,33,0,0,0",
        "17,34,0,1,1",
        "18,35,0,1,1",
        "19,35,1,0,W",
        "20,35,1,0,0",
        "21,41,1,6,6",
        "22,43,1,2,2",
        "23,44,1,1,1",
        "24,45,1,1,1",
        "25,45,2,0,W",
        "26,46,2,1,1",
        "27,46,2,0,0",
        "28,46,2,0,0",
        "29,50,2,4,4",
        "30,54,2,4,4",
        "31,55,2,1,1",
        "32,55,2,0,0",
        "33,61,2,6,6",
        "34,61,2,0,0",
        "35,65,2,4,4",
        "36,65,3,0,W",
        "37,66,3,1,1",
        "38,67,3,1,1",
        "39,68,3,1,1",
        "40,69,3,1,1",
        "41,71,3,2,Wd",
        "42,72,3,1,1",
        "43,72,3,0,0",
        "44,73,3,1,1",
        "45,74,3,1,1",
        "46,75,3,1,1",
        "47,76,3,1,1",
        "48,82,3,6,6",
        "49,83,3,1,1",
        "50,87,3,4,4",
        "51,91,3,4,4",
        "52,95,3,4,4",
        "53,95,3,0,0",
        "54,101,3,6,6",
        "55,102,3,1,1",
        "56,103,3,1,1",
        "57,104,3,1,1",
        "58,105,3,1,1",
        "59,111,3,6,6",
        "60,115,3,4,4",
        "61,117,3,2,Wd",
        "62,118,3,1,1",
        "63,118,3,0,0",
        "64,119,3,1,1",
        "65,120,3,1,1",
        "66,120,3,0,0",
        "67,121,3,1,1",
        "68,127,3,6,6",
        "69,128,3,1,1",
        "70,129,3,1,1",
        "71,133,3,4,4",
        "72,134,3,1,1",
        "73,135,3,1,1",
        "74,136,3,1,1",
        "75,136,4,0,W",
        "76,140,4,4,4",
        "77,140,5,0,W",
        "78,141,5,1,1",
        "79,142,5,1,1",
        "80,143,5,1,1",
        "81,144,5,1,1",
        "82,145,5,1,1",
        "83,151,5,6,6",
        "84,152,5,1,1",
        "85,153,5,1,1",
        "86,159,5,6,6",
        "87,159,5,0,0",
        "88,163,5,4,4",
        "89,167,5,4,4",
        "90,173,5,6,6",
        "91,174,5,1,1",
        "92,178,5,4,4",
        "93,181,5,3,Wd",
        "94,182,5,1,1",
        "95,186,5,4,4",
        "96,187,5,1,1",
        "97,190,5,3,Wd/Wd",
        "98,190,5,0,0",
        "99,191,5,1,1",
        "100,192,5,1,1",
        "101,193,5,1,1",
        "102,194,5,1,1",
        "103,200,5,6,6",
        "104,204,5,4,4",
        "105,210,5,6,6",
        "106,210,6,0,W",
        "107,211,6,1,1",
        "108,217,6,6,6",
        "109,217,6,0,0",
        "110,223,6,6,6",
        "111,223,7,0,W",
        "112,229,7,6,6",
        "113,230,7,1,1",
        "114,233,7,3,3",
        "115,234,8,1,W",
        "116,236,8,2,2",
        "117,242,8,6,6",
        "118,243,8,1,1",
        "119,247,8,4,4",
        "120,247,9,0,W"
      ]
    }
  ],
  "error": null
}