{
  "innings": [
    {
      "bat_team": "Mumbai Indians",
      "bowl_team": "Punjab Kings",
      "innings_id": 1,
      "score": {
        "runs": 195,
        "wickets": 6,
        "overs": 20,
        "run_rate": 9.75,
        "declared": false
      },
      "extras": {
        "total": 8,
        "wides": 4,
        "no_balls": 0,
        "byes": 0,
        "leg_byes": 4
      },
      "batsmen": [
        {
          "name": "Ryan Rickelton",
          "runs": 2,
          "balls": 8,
          "fours": 0,
          "sixes": 0,
          "strike_rate": 25,
          "out_desc": "c Shashank Singh b Arshdeep Singh",
          "is_captain": false,
          "is_keeper": false,
          "not_out": false
        },
        {
          "name": "Quinton de Kock",
          "runs": 112,
          "balls": 60,
          "fours": 8,
          "sixes": 7,
          "strike_rate": 186.67,
          "out_desc": "not out",
          "is_captain": false,
          "is_keeper": true,
          "not_out": false
        },
        {
          "name": "Suryakumar Yadav",
          "runs": 0,
          "balls": 1,
          "fours": 0,
          "sixes": 0,
          "strike_rate": 0,
          "out_desc": "c Yuzvendra Chahal b Arshdeep Singh",
          "is_captain": false,
          "is_keeper": false,
          "not_out": false
        },
        {
          "name": "Naman Dhir",
          "runs": 50,
          "balls": 31,
          "fours": 3,
          "sixes": 3,
          "strike_rate": 161.29,
          "out_desc": "c Xavier Bartlett b Shashank Singh",
          "is_captain": false,
          "is_keeper": false,
          "not_out": false
        },
        {
          "name": "Hardik Pandya",
          "runs": 14,
          "balls": 12,
          "fours": 0,
          "sixes": 1,
          "strike_rate": 116.67,
          "out_desc": "c Xavier Bartlett b Marco Jansen",
          "is_captain": true,
          "is_keeper": false,
          "not_out": false
        },
        {
          "name": "Sherfane Rutherford",
          "runs": 1,
          "balls": 5,
          "fours": 0,
          "sixes": 0,
          "strike_rate": 20,
          "out_desc": "b Arshdeep Singh",
          "is_captain": false,
          "is_keeper": false,
          "not_out": false
        },
        {
          "name": "Tilak Varma",
          "runs": 8,
          "balls": 3,
          "fours": 2,
          "sixes": 0,
          "strike_rate": 266.67,
          "out_desc": "run out (Vijaykumar Vyshak)",
          "is_captain": false,
          "is_keeper": false,
          "not_out": false
        },
        {
          "name": "Mayank Rawat",
          "runs": 0,
          "balls": 0,
          "fours": 0,
          "sixes": 0,
          "strike_rate": 0,
          "out_desc": "not out",
          "is_captain": false,
          "is_keeper": false,
          "not_out": false
        },
        {
          "name": "Shardul Thakur",
          "runs": 0,
          "balls": 0,
          "fours": 0,
          "sixes": 0,
          "strike_rate": 0,
          "out_desc": "",
          "is_captain": false,
          "is_keeper": false,
          "not_out": true
        },
        {
          "name": "Deepak Chahar",
          "runs": 0,
          "balls": 0,
          "fours": 0,
          "sixes": 0,
          "strike_rate": 0,
          "out_desc": "",
          "is_captain": false,
          "is_keeper": false,
          "not_out": true
        },
        {
          "name": "Jasprit Bumrah",
          "runs": 0,
          "balls": 0,
          "fours": 0,
          "sixes": 0,
          "strike_rate": 0,
          "out_desc": "",
          "is_captain": false,
          "is_keeper": false,
          "not_out": true
        }
      ],
      "bowlers": [
        {
          "name": "Arshdeep Singh",
          "overs": 4,
          "balls": 24,
          "maidens": 0,
          "runs": 22,
          "wickets": 3,
          "economy": 5.5,
          "wides": 1,
          "no_balls": 0,
          "dots": 0
        },
        {
          "name": "Marco Jansen",
          "overs": 4,
          "balls": 24,
          "maidens": 0,
          "runs": 30,
          "wickets": 1,
          "economy": 7.5,
          "wides": 1,
          "no_balls": 0,
          "dots": 0
        },
        {
          "name": "Xavier Bartlett",
          "overs": 4,
          "balls": 24,
          "maidens": 0,
          "runs": 39,
          "wickets": 0,
          "economy": 9.8,
          "wides": 0,
          "no_balls": 0,
          "dots": 0
        },
        {
          "name": "Vijaykumar Vyshak",
          "overs": 3,
          "balls": 18,
          "maidens": 0,
          "runs": 36,
          "wickets": 0,
          "economy": 12,
          "wides": 1,
          "no_balls": 0,
          "dots": 0
        },
        {
          "name": "Yuzvendra Chahal",
          "overs": 3,
          "balls": 18,
          "maidens": 0,
          "runs": 45,
          "wickets": 0,
          "economy": 15,
          "wides": 1,
          "no_balls": 0,
          "dots": 0
        },
        {
          "name": "Shashank Singh",
          "overs": 2,
          "balls": 12,
          "maidens": 0,
          "runs": 19,
          "wickets": 1,
          "economy": 9.5,
          "wides": 0,
          "no_balls": 0,
          "dots": 0
        }
      ],
      "fow": [
        {
          "name": "Ryan Rickelton",
          "runs": 12,
          "over": 2.1,
          "wkt_n": 1
        },
        {
          "name": "Suryakumar Yadav",
          "runs": 12,
          "over": 2.2,
          "wkt_n": 2
        },
        {
          "name": "Naman Dhir",
          "runs": 134,
          "over": 13.4,
          "wkt_n": 3
        },
        {
          "name": "Hardik Pandya",
          "runs": 175,
          "over": 17.3,
          "wkt_n": 4
        },
        {
          "name": "Sherfane Rutherford",
          "runs": 182,
          "over": 18.5,
          "wkt_n": 5
        },
        {
          "name": "Tilak Varma",
          "runs": 193,
          "over": 19.5,
          "wkt_n": 6
        }
      ]
    },
    {
      "bat_team": "Punjab Kings",
      "bowl_team": "Mumbai Indians",
      "innings_id": 2,
      "score": {
        "runs": 198,
        "wickets": 3,
        "overs": 16.3,
        "run_rate": 12,
        "declared": false
      },
      "extras": {
        "total": 10,
        "wides": 9,
        "no_balls": 1,
        "byes": 0,
        "leg_byes": 0
      },
      "batsmen": [
        {
          "name": "Priyansh Arya",
          "runs": 15,
          "balls": 9,
          "fours": 2,
          "sixes": 1,
          "strike_rate": 166.67,
          "out_desc": "c Deepak Chahar b AM Ghazanfar",
          "is_captain": false,
          "is_keeper": false,
          "not_out": false
        },
        {
          "name": "Prabhsimran Singh",
          "runs": 80,
          "balls": 39,
          "fours": 11,
          "sixes": 2,
          "strike_rate": 205.13,
          "out_desc": "not out",
          "is_captain": false,
          "is_keeper": true,
          "not_out": false
        },
        {
          "name": "Cooper Connolly",
          "runs": 17,
          "balls": 12,
          "fours": 1,
          "sixes": 2,
          "strike_rate": 141.67,
          "out_desc": "c Quinton de Kock b AM Ghazanfar",
          "is_captain": false,
          "is_keeper": false,
          "not_out": false
        },
        {
          "name": "Shreyas Iyer",
          "runs": 66,
          "balls": 35,
          "fours": 5,
          "sixes": 4,
          "strike_rate": 188.57,
          "out_desc": "c Naman Dhir b Shardul Thakur",
          "is_captain": true,
          "is_keeper": false,
          "not_out": false
        },
        {
          "name": "Marcus Stoinis",
          "runs": 10,
          "balls": 5,
          "fours": 2,
          "sixes": 0,
          "strike_rate": 200,
          "out_desc": "not out",
          "is_captain": false,
          "is_keeper": false,
          "not_out": false
        },
        {
          "name": "Shashank Singh",
          "runs": 0,
          "balls": 0,
          "fours": 0,
          "sixes": 0,
          "strike_rate": 0,
          "out_desc": "",
          "is_captain": false,
          "is_keeper": false,
          "not_out": true
        },
        {
          "name": "Marco Jansen",
          "runs": 0,
          "balls": 0,
          "fours": 0,
          "sixes": 0,
          "strike_rate": 0,
          "out_desc": "",
          "is_captain": false,
          "is_keeper": false,
          "not_out": true
        },
        {
          "name": "Xavier Bartlett",
          "runs": 0,
          "balls": 0,
          "fours": 0,
          "sixes": 0,
          "strike_rate": 0,
          "out_desc": "",
          "is_captain": false,
          "is_keeper": false,
          "not_out": true
        },
        {
          "name": "Vijaykumar Vyshak",
          "runs": 0,
          "balls": 0,
          "fours": 0,
          "sixes": 0,
          "strike_rate": 0,
          "out_desc": "",
          "is_captain": false,
          "is_keeper": false,
          "not_out": true
        },
        {
          "name": "Arshdeep Singh",
          "runs": 0,
          "balls": 0,
          "fours": 0,
          "sixes": 0,
          "strike_rate": 0,
          "out_desc": "",
          "is_captain": false,
          "is_keeper": false,
          "not_out": true
        },
        {
          "name": "Yuzvendra Chahal",
          "runs": 0,
          "balls": 0,
          "fours": 0,
          "sixes": 0,
          "strike_rate": 0,
          "out_desc": "",
          "is_captain": false,
          "is_keeper": false,
          "not_out": true
        }
      ],
      "bowlers": [
        {
          "name": "Deepak Chahar",
          "overs": 2.3,
          "balls": 15,
          "maidens": 0,
          "runs": 45,
          "wickets": 0,
          "economy": 18,
          "wides": 3,
          "no_balls": 0,
          "dots": 0
        },
        {
          "name": "Jasprit Bumrah",
          "overs": 4,
          "balls": 24,
          "maidens": 0,
          "runs": 41,
          "wickets": 0,
          "economy": 10.2,
          "wides": 1,
          "no_balls": 1,
          "dots": 0
        },
        {
          "name": "AM Ghazanfar",
          "overs": 4,
          "balls": 24,
          "maidens": 0,
          "runs": 31,
          "wickets": 2,
          "economy": 7.8,
          "wides": 0,
          "no_balls": 0,
          "dots": 0
        },
        {
          "name": "Hardik Pandya",
          "overs": 3,
          "balls": 18,
          "maidens": 0,
          "runs": 39,
          "wickets": 0,
          "economy": 13,
          "wides": 1,
          "no_balls": 0,
          "dots": 0
        },
        {
          "name": "Shardul Thakur",
          "overs": 3,
          "balls": 18,
          "maidens": 0,
          "runs": 42,
          "wickets": 1,
          "economy": 14,
          "wides": 4,
          "no_balls": 0,
          "dots": 0
        }
      ],
      "fow": [
        {
          "name": "Priyansh Arya",
          "runs": 27,
          "over": 2.2,
          "wkt_n": 1
        },
        {
          "name": "Cooper Connolly",
          "runs": 45,
          "over": 4.3,
          "wkt_n": 2
        },
        {
          "name": "Shreyas Iyer",
          "runs": 184,
          "over": 15.3,
          "wkt_n": 3
        }
      ]
    }
  ],
  "error": null
}