{
  "innings": [
    {
      "bat_team": "Rajasthan Royals",
      "bowl_team": "Delhi Capitals",
      "innings_id": 1,
      "score": {
        "runs": 6,
        "wickets": 1,
        "overs": 0.5,
        "run_rate": 7.2,
        "declared": false
      },
      "extras": {
        "total": 0,
        "wides": 0,
        "no_balls": 0,
        "byes": 0,
        "leg_byes": 0
      },
      "batsmen": [
        {
          "name": "Yashasvi Jaiswal",
          "runs": 6,
          "balls": 3,
          "fours": 0,
          "sixes": 1,
          "strike_rate": 200,
          "out_desc": "c and b Mitchell Starc",
          "is_captain": false,
          "is_keeper": false,
          "not_out": false
        },
        {
          "name": "Vaibhav Sooryavanshi",
          "runs": 0,
          "balls": 0,
          "fours": 0,
          "sixes": 0,
          "strike_rate": 0,
          "out_desc": "batting",
          "is_captain": false,
          "is_keeper": false,
          "not_out": false
        },
        {
          "name": "Dhruv Jurel",
          "runs": 0,
          "balls": 2,
          "fours": 0,
          "sixes": 0,
          "strike_rate": 0,
          "out_desc": "batting",
          "is_captain": false,
          "is_keeper": true,
          "not_out": false
        },
        {
          "name": "Riyan Parag",
          "runs": 0,
          "balls": 0,
          "fours": 0,
          "sixes": 0,
          "strike_rate": 0,
          "out_desc": "",
          "is_captain": true,
          "is_keeper": false,
          "not_out": true
        },
        {
          "name": "Donovan Ferreira",
          "runs": 0,
          "balls": 0,
          "fours": 0,
          "sixes": 0,
          "strike_rate": 0,
          "out_desc": "",
          "is_captain": false,
          "is_keeper": false,
          "not_out": true
        },
        {
          "name": "Ravindra Jadeja",
          "runs": 0,
          "balls": 0,
          "fours": 0,
          "sixes": 0,
          "strike_rate": 0,
          "out_desc": "",
          "is_captain": false,
          "is_keeper": false,
          "not_out": true
        },
        {
          "name": "Shubham Dubey",
          "runs": 0,
          "balls": 0,
          "fours": 0,
          "sixes": 0,
          "strike_rate": 0,
          "out_desc": "",
          "is_captain": false,
          "is_keeper": false,
          "not_out": true
        },
        {
          "name": "Jofra Archer",
          "runs": 0,
          "balls": 0,
          "fours": 0,
          "sixes": 0,
          "strike_rate": 0,
          "out_desc": "",
          "is_captain": false,
          "is_keeper": false,
          "not_out": true
        },
        {
          "name": "Ravi Bishnoi",
          "runs": 0,
          "balls": 0,
          "fours": 0,
          "sixes": 0,
          "strike_rate": 0,
          "out_desc": "",
          "is_captain": false,
          "is_keeper": false,
          "not_out": true
        },
        {
          "name": "Nandre Burger",
          "runs": 0,
          "balls": 0,
          "fours": 0,
          "sixes": 0,
          "strike_rate": 0,
          "out_desc": "",
          "is_captain": false,
          "is_keeper": false,
          "not_out": true
        },
        {
          "name": "Brijesh Sharma",
          "runs": 0,
          "balls": 0,
          "fours": 0,
          "sixes": 0,
          "strike_rate": 0,
          "out_desc": "",
          "is_captain": false,
          "is_keeper": false,
          "not_out": true
        }
      ],
      "bowlers": [
        {
          "name": "Mitchell Starc",
          "overs": 0.5,
          "balls": 5,
          "maidens": 0,
          "runs": 6,
          "wickets": 1,
          "economy": 7.2,
          "wides": 0,
          "no_balls": 0,
          "dots": 0
        }
      ],
      "fow": [
        {
          "name": "Yashasvi Jaiswal",
          "runs": 6,
          "over": 0.3,
          "wkt_n": 1
        }
      ]
    }
  ],
  "error": null
}